{"legislative_session": "26", "identifier": "B26-0456", "title": "Private Vehicle-for-Hire Operator Clarification Temporary Amendment Act of 2025", "from_organization": "~{\"classification\": \"legislature\"}", "classification": ["bill"], "subject": [], "abstracts": [], "other_titles": [], "other_identifiers": [], "actions": [{"description": "B26-0456 Introduced by Councilmember Nadeau at Office of the Secretary", "date": "2025-11-03T05:00:00+00:00", "organization_id": "~{\"classification\": \"legislature\"}", "classification": ["introduction"], "related_entities": []}, {"description": "Retained by the Council", "date": "2025-11-04T05:00:00+00:00", "organization_id": "~{\"classification\": \"legislature\"}", "classification": [], "related_entities": []}, {"description": "First Reading", "date": "2025-11-04T05:00:00+00:00", "organization_id": "~{\"classification\": \"legislature\"}", "classification": ["reading-1"], "related_entities": []}, {"description": "Notice of Intent to Act on B26-0456 Published in the District of Columbia Register", "date": "2025-11-07T05:00:00+00:00", "organization_id": "~{\"classification\": \"legislature\"}", "classification": [], "related_entities": []}, {"description": "Final Reading, CC", "date": "2025-12-02T05:00:00+00:00", "organization_id": "~{\"classification\": \"legislature\"}", "classification": ["reading-3"], "related_entities": []}], "sponsorships": [{"name": "Nadeau, Brianne K.", "classification": "primary", "entity_type": "person", "primary": true, "person_id": "~{\"name\": \"Nadeau, Brianne K.\"}", "organization_id": null}], "related_bills": [], "versions": [{"note": "Introduction", "links": [{"url": "https://lims.dccouncil.gov/downloads/LIMS/60653/Introduction/B26-0456-Introduction.pdf?Id=226350", "media_type": "application/pdf"}], "date": "", "classification": ""}, {"note": "Engrossment", "links": [{"url": "https://lims.dccouncil.gov/downloads/LIMS/60653/Meeting1/Engrossment/B26-0456-Engrossment1.pdf?Id=228331", "media_type": "application/pdf"}], "date": "", "classification": ""}], "documents": [], "citations": [], "sources": [{"url": "https://lims.dccouncil.gov/api/v2/PublicData/BulkData/1/26", "note": ""}, {"url": "https://lims.dccouncil.gov/Legislation/B26-0456", "note": ""}], "extras": {}, "jurisdiction": {"id": "ocd-jurisdiction/country:us/district:dc/government", "name": "District of Columbia", "classification": "state", "division_id": "ocd-division/country:us/district:dc"}, "scraped_at": "2025-12-08T08:38:45+00:00", "_id": "4f07d31c-d411-11f0-a4ed-0eda20d009db"}